{"cameraMode":{"drawMode":0,"name":"Shaded","section":"Shading Mode"},"sceneLighting":true,"audioPlay":false,"sceneViewState":{"m_AlwaysRefresh":false,"showFog":true,"showSkybox":true,"showFlares":true,"showImageEffects":true,"showParticleSystems":true,"showVisualEffectGraphs":true,"m_FxEnabled":true},"in2DMode":false,"pivot":{"x":700.314697265625,"y":38.064430236816409,"z":0.0},"rotation":{"x":0.5764645934104919,"y":0.002451359061524272,"z":-0.001729397801682353,"w":0.8171169757843018},"size":862.5283203125,"orthographic":false}